MANIFEST.in
README.rst
setup.cfg
setup.py
bin/isign
bin/isign_export_creds.sh
bin/isign_guess_mobileprovision.sh
bin/multisign
isign/__init__.py
isign/archive.py
isign/bundle.py
isign/code_resources.py
isign/code_resources_template.xml
isign/codesig.py
isign/exceptions.py
isign/isign.py
isign/macho.py
isign/macho_cs.py
isign/makesig.py
isign/signable.py
isign/signer.py
isign/version.json
isign.egg-info/PKG-INFO
isign.egg-info/SOURCES.txt
isign.egg-info/dependency_links.txt
isign.egg-info/requires.txt
isign.egg-info/top_level.txt
isign/apple_credentials/applecerts.pem